Workbook

Sheet Как пользоваться
A1: Контент-план студии «Форма сайта»: 150 статей и сервисы
A3: Сколько это по времени
A4: 150 статей при двух публикациях в неделю — это полтора года. Не пугаться: план сделан так, что статьи приоритета 1 дают основную часть результата, остальное — задел на потом.
A5: Порядок: сначала статьи приоритета 1 (их 79), потом 2 (58), потом 3 (13). Внутри приоритета — сначала опорные (помечены в плане), они собирают вокруг себя остальные ссылками.
A7: Три правила, без которых статьи не окупятся
A8: 1. Каждая статья ведёт на конкретную страницу услуги — колонка «Ведёт на». Статья без выхода на услугу собирает трафик и не приносит заявок.
A9: 2. В каждой статье — минимум одна цифра или скриншот из нашей практики: замер скорости, стоимость заявки, конверсия. Это отличает нас от рерайта, который уже есть в выдаче.
A10: 3. Нишевые статьи (кластер 1) публикуются парой со своим демо-лендингом: статья ссылается на живой пример, демо — на статью.
A12: Двойное применение
A13: Статьи кластера 1 и опорные статьи по Директу — это ещё и материал для продаж. Менеджер после звонка отправляет ссылку: «вот разбор по вашей нише». Работает лучше презентации.
A15: Про объём
A16: Указанные знаки — ориентир под глубину темы, а не норма для копирайтера. Короткая честная статья лучше раздутой. Если тема закрывается в 3000 знаков — пишем 3000.

Sheet Каталог статей
A1: № | B1: Заголовок | C1: Кластер | D1: Целевой запрос | E1: Интент | F1: Этап воронки | G1: Формат | H1: Объём, знаков | I1: Ведёт на | J1: План статьи | K1: Приоритет
A2: 1 | B2: Где брать заказы на бурение скважин: 8 каналов и сколько стоит заявка в каждом | C2: 1. Ниши | D2: как получать заявки на бурение скважин | E2: информационный | F2: холодный | G2: обзор каналов | H2: 8000–10000 | I2: /sait-dlya/burenie-skvazhin/ | J2: Авито · Яндекс Карты · Директ · сарафан · агрегаторы · соцсети · партнёры · офлайн. По каждому: сколько стоит заявка, сколько времени до первых обращений, кому подходит. Вывод: связка «карты + сайт + Директ» и почему без сайта остальное работает хуже. | K2: 1
A3: 2 | B3: Сайт для бурения скважин: что обязательно должно быть, чтобы звонили | C3: 1. Ниши | D3: что должно быть на сайте буровой компании | E3: информационный | F3: тёплый | G3: разбор структуры | H3: 6000–8000 | I3: /sait-dlya/burenie-skvazhin/ | J3: Первый экран с ценой · калькулятор по параметрам работ · объекты с адресом и цифрами · отзывы с источником · договор и гарантия · кнопка звонка на мобильном. Каждый блок — на живом примере из нашего демо. | K3: 1
A4: 3 | B4: Сколько стоит сайт для бурения скважин и из чего складывается цена | C4: 1. Ниши | D4: сайт для бурения скважин цена | E4: коммерческий | F4: горячий | G4: разбор цены | H4: 5000–6000 | I4: /sait-dlya/burenie-skvazhin/ | J4: Три уровня: шаблон · лендинг под нишу · сайт с калькулятором и интеграциями. Что входит, что нет, сроки. Честно: когда хватит Авито и сайт не нужен. | K4: 2
A5: 4 | B5: Где брать заказы на заборы: 8 каналов и сколько стоит заявка в каждом | C5: 1. Ниши | D5: как получать заявки на заборы | E5: информационный | F5: холодный | G5: обзор каналов | H5: 8000–10000 | I5: /sait-dlya/zabory/ | J5: Авито · Яндекс Карты · Директ · сарафан · агрегаторы · соцсети · партнёры · офлайн. По каждому: сколько стоит заявка, сколько времени до первых обращений, кому подходит. Вывод: связка «карты + сайт + Директ» и почему без сайта остальное работает хуже. | K5: 1
A6: 5 | B6: Сайт для заборов: что обязательно должно быть, чтобы звонили | C6: 1. Ниши | D6: что должно быть на сайте компании по заборов | E6: информационный | F6: тёплый | G6: разбор структуры | H6: 6000–8000 | I6: /sait-dlya/zabory/ | J6: Первый экран с ценой · калькулятор по параметрам работ · объекты с адресом и цифрами · отзывы с источником · договор и гарантия · кнопка звонка на мобильном. Каждый блок — на живом примере из нашего демо. | K6: 1
A7: 6 | B7: Сколько стоит сайт для заборов и из чего складывается цена | C7: 1. Ниши | D7: сайт для заборов цена | E7: коммерческий | F7: горячий | G7: разбор цены | H7: 5000–6000 | I7: /sait-dlya/zabory/ | J7: Три уровня: шаблон · лендинг под нишу · сайт с калькулятором и интеграциями. Что входит, что нет, сроки. Честно: когда хватит Авито и сайт не нужен. | K7: 2
A8: 7 | B8: Где брать заказы на септики: 8 каналов и сколько стоит заявка в каждом | C8: 1. Ниши | D8: как получать заявки на септики | E8: информационный | F8: холодный | G8: обзор каналов | H8: 8000–10000 | I8: /sait-dlya/septiki/ | J8: Авито · Яндекс Карты · Директ · сарафан · агрегаторы · соцсети · партнёры · офлайн. По каждому: сколько стоит заявка, сколько времени до первых обращений, кому подходит. Вывод: связка «карты + сайт + Директ» и почему без сайта остальное работает хуже. | K8: 1
A9: 8 | B9: Сайт для септиков: что обязательно должно быть, чтобы звонили | C9: 1. Ниши | D9: что должно быть на сайте монтажников септиков | E9: информационный | F9: тёплый | G9: разбор структуры | H9: 6000–8000 | I9: /sait-dlya/septiki/ | J9: Первый экран с ценой · калькулятор по параметрам работ · объекты с адресом и цифрами · отзывы с источником · договор и гарантия · кнопка звонка на мобильном. Каждый блок — на живом примере из нашего демо. | K9: 1
A10: 9 | B10: Сколько стоит сайт для септиков и из чего складывается цена | C10: 1. Ниши | D10: сайт для септиков цена | E10: коммерческий | F10: горячий | G10: разбор цены | H10: 5000–6000 | I10: /sait-dlya/septiki/ | J10: Три уровня: шаблон · лендинг под нишу · сайт с калькулятором и интеграциями. Что входит, что нет, сроки. Честно: когда хватит Авито и сайт не нужен. | K10: 2
A11: 10 | B11: Где брать заказы на кровлю: 8 каналов и сколько стоит заявка в каждом | C11: 1. Ниши | D11: как получать заявки на кровлю | E11: информационный | F11: холодный | G11: обзор каналов | H11: 8000–10000 | I11: /sait-dlya/krovlya/ | J11: Авито · Яндекс Карты · Директ · сарафан · агрегаторы · соцсети · партнёры · офлайн. По каждому: сколько стоит заявка, сколько времени до первых обращений, кому подходит. Вывод: связка «карты + сайт + Директ» и почему без сайта остальное работает хуже. | K11: 1
A12: 11 | B12: Сайт для кровельных работ: что обязательно должно быть, чтобы звонили | C12: 1. Ниши | D12: что должно быть на сайте кровельщиков | E12: информационный | F12: тёплый | G12: разбор структуры | H12: 6000–8000 | I12: /sait-dlya/krovlya/ | J12: Первый экран с ценой · калькулятор по параметрам работ · объекты с адресом и цифрами · отзывы с источником · договор и гарантия · кнопка звонка на мобильном. Каждый блок — на живом примере из нашего демо. | K12: 1
A13: 12 | B13: Сколько стоит сайт для кровельных работ и из чего складывается цена | C13: 1. Ниши | D13: сайт для кровельных работ цена | E13: коммерческий | F13: горячий | G13: разбор цены | H13: 5000–6000 | I13: /sait-dlya/krovlya/ | J13: Три уровня: шаблон · лендинг под нишу · сайт с калькулятором и интеграциями. Что входит, что нет, сроки. Честно: когда хватит Авито и сайт не нужен. | K13: 2
... A151: 150 | B151: Почему клиенты выбирают не самого дешёвого | C151: 7. Бизнес подрядчика | D151: почему выбирают дорогих подрядчиков | E151: информационный | F151: холодный | G151: разбор | H151: 5000–6000 | I151: / | J151: Что снимает риск в глазах заказчика. Как это показать на сайте. | K151: 2

Sheet Сводка
A1: Кластер | B1: Статей | C1: Приоритет 1 | D1: Приоритет 2 | E1: Приоритет 3
A2: 1. Ниши | B2: =COUNTIF('Каталог статей'!$C$2:$C$151,A2) | C2: =COUNTIFS('Каталог статей'!$C$2:$C$151,A2,'Каталог статей'!$K$2:$K$151,1) | D2: =COUNTIFS('Каталог статей'!$C$2:$C$151,A2,'Каталог статей'!$K$2:$K$151,2) | E2: =COUNTIFS('Каталог статей'!$C$2:$C$151,A2,'Каталог статей'!$K$2:$K$151,3)
A3: 2. Заявки и конверсия | B3: =COUNTIF('Каталог статей'!$C$2:$C$151,A3) | C3: =COUNTIFS('Каталог статей'!$C$2:$C$151,A3,'Каталог статей'!$K$2:$K$151,1) | D3: =COUNTIFS('Каталог статей'!$C$2:$C$151,A3,'Каталог статей'!$K$2:$K$151,2) | E3: =COUNTIFS('Каталог статей'!$C$2:$C$151,A3,'Каталог статей'!$K$2:$K$151,3)
A4: 3. Яндекс Директ | B4: =COUNTIF('Каталог статей'!$C$2:$C$151,A4) | C4: =COUNTIFS('Каталог статей'!$C$2:$C$151,A4,'Каталог статей'!$K$2:$K$151,1) | D4: =COUNTIFS('Каталог статей'!$C$2:$C$151,A4,'Каталог статей'!$K$2:$K$151,2) | E4: =COUNTIFS('Каталог статей'!$C$2:$C$151,A4,'Каталог статей'!$K$2:$K$151,3)
A5: 4. SEO и Яндекс Карты | B5: =COUNTIF('Каталог статей'!$C$2:$C$151,A5) | C5: =COUNTIFS('Каталог статей'!$C$2:$C$151,A5,'Каталог статей'!$K$2:$K$151,1) | D5: =COUNTIFS('Каталог статей'!$C$2:$C$151,A5,'Каталог статей'!$K$2:$K$151,2) | E5: =COUNTIFS('Каталог статей'!$C$2:$C$151,A5,'Каталог статей'!$K$2:$K$151,3)
A6: 5. Скорость и техника | B6: =COUNTIF('Каталог статей'!$C$2:$C$151,A6) | C6: =COUNTIFS('Каталог статей'!$C$2:$C$151,A6,'Каталог статей'!$K$2:$K$151,1) | D6: =COUNTIFS('Каталог статей'!$C$2:$C$151,A6,'Каталог статей'!$K$2:$K$151,2) | E6: =COUNTIFS('Каталог статей'!$C$2:$C$151,A6,'Каталог статей'!$K$2:$K$151,3)
A7: 6. Деньги и выбор подрядчика | B7: =COUNTIF('Каталог статей'!$C$2:$C$151,A7) | C7: =COUNTIFS('Каталог статей'!$C$2:$C$151,A7,'Каталог статей'!$K$2:$K$151,1) | D7: =COUNTIFS('Каталог статей'!$C$2:$C$151,A7,'Каталог статей'!$K$2:$K$151,2) | E7: =COUNTIFS('Каталог статей'!$C$2:$C$151,A7,'Каталог статей'!$K$2:$K$151,3)
A8: 7. Бизнес подрядчика | B8: =COUNTIF('Каталог статей'!$C$2:$C$151,A8) | C8: =COUNTIFS('Каталог статей'!$C$2:$C$151,A8,'Каталог статей'!$K$2:$K$151,1) | D8: =COUNTIFS('Каталог статей'!$C$2:$C$151,A8,'Каталог статей'!$K$2:$K$151,2) | E8: =COUNTIFS('Каталог статей'!$C$2:$C$151,A8,'Каталог статей'!$K$2:$K$151,3)
A9: Итого | B9: =SUM(B2:B8) | C9: =SUM(C2:C8) | D9: =SUM(D2:D8) | E9: =SUM(E2:E8)
A11: При двух статьях в неделю приоритет 1 (79 статей) закрывается примерно за 10 месяцев, весь план — за 19.

Sheet Сервисы
A1: Сервис | B1: Тип | C1: Приоритет | D1: Что делает | E1: Польза для заявок | F1: Сложность | G1: Почему именно он | H1: Чем делать
A2: Проверка сайта подрядчика | B2: Диагностика | C2: 1 | D2: Вводят адрес сайта — получают отчёт: скорость, мобильная версия, есть ли цены, форма, калькулятор, отзывы, мессенджеры, HTTPS. Балл и список правок по убыванию важности. | E2: Высокая | F2: Средняя | G2: Наш скрипт продаж, превращённый в автомат. Человек сам приносит свой адрес и узнаёт о проблемах — дальше остаётся позвонить. Плюс собирает базу: кто проверил, тот думает о сайте. | H2: PageSpeed Insights API (бесплатный ключ) + свой разбор разметки. Расширенный отчёт — за контакт.
A3: Сравнение с конкурентом | B3: Диагностика | C3: 1 | D3: Два адреса — таблица различий по тем же параметрам. Наглядно видно отставание. | E3: Высокая | F3: Средняя | G3: Самый сильный аргумент в продаже: не мы говорим, что сайт плохой, а таблица рядом с конкурентом. Менеджер открывает это прямо на звонке. | H3: Тот же движок, что и проверка, на два адреса.
A4: Калькулятор стоимости заявки | B4: Расчёт | C4: 1 | D4: Расход на рекламу, число заявок, конверсия в сделку, средний чек — на выходе цена заявки, цена клиента и предельная сумма, которую можно платить за заявку. | E4: Высокая | F4: Низкая | G4: Подрядчики этого не считают. Посчитав, многие впервые видят, что реклама убыточна — и это ровно тот момент, когда нужны мы. | H4: Чистая арифметика на клиенте, без сервера. День работы.
A5: Конфигуратор сайта | B5: Расчёт | C5: 1 | D5: Ниша, набор блоков, калькулятор, квиз, интеграции — цена, срок и состав работ. Внизу структура будущего лендинга под выбранную нишу. | E5: Высокая | F5: Низкая | G5: Наш же принцип «цена до звонка», применённый к себе. Отсекает тех, кому дорого, и приводит подготовленных. | H5: Тот же калькулятор, что мы ставим клиентам. Переиспользуем код.
A6: Библиотека демо по нишам | B6: Контент | C6: 1 | D6: Живые демо-лендинги по каждой нише, которые можно открыть и потрогать: калькулятор, квиз, формы. | E6: Высокая | F6: Низкая | G6: Два демо уже есть, будет восемнадцать. Работает трижды: портфолио, посадочные под нишевые запросы и ссылка, которую менеджер шлёт после звонка. | H6: Уже собираются генератором. Нужна только витрина со списком.
A7: Калькулятор бюджета Директа | B7: Расчёт | C7: 2 | D7: Ниша, город, нужное число заявок — ориентир по месячному бюджету и цене клика. | E7: Средняя | F7: Средняя | G7: Приводит тех, кто только планирует рекламу. Продаёт связку «лендинг + Директ». | H7: Нужны ориентиры по ценам клика — собрать из своей статистики, честно пометить как оценку.
A8: Генератор структуры лендинга | B8: Инструмент | C8: 2 | D8: Выбрал нишу — получил структуру блоков с пояснением, зачем каждый и что туда написать. | E8: Средняя | F8: Низкая | G8: Даёт пользу сразу и без оплаты, показывает экспертизу. Часть после этого просит сделать под ключ. | H8: Данные уже есть в генераторе лендингов.
A9: База минус-слов по нишам | B9: Контент | C9: 2 | D9: Готовые списки минус-слов для строительных ниш, файлом для загрузки в Директ. | E9: Средняя | F9: Низкая | G9: Классический лид-магнит: скачивают в обмен на контакт, и это ровно наша аудитория — те, кто уже запускает рекламу. | H9: Составить руками по нишам, обновлять раз в квартал.
A10: Чек-лист приёмки сайта | B10: Инструмент | C10: 2 | D10: Интерактивный чек-лист из 20 пунктов: отмечаешь, видишь итоговый балл и что исправить. | E10: Средняя | F10: Низкая | G10: Ловит тех, кому сайт делает кто-то другой. Часть возвращается, когда находит проблемы. | H10: Статика плюс немного скриптов.
A11: Калькуляторы для чужих сайтов | B11: Инструмент | C11: 3 | D11: Готовые калькуляторы под ниши, которые подрядчик может встроить к себе кодом. | E11: Средняя | F11: Высокая | G11: Приводит нужную аудиторию и показывает продукт в деле, но требует поддержки и техподдержки чужих сайтов. Браться только после запуска первой пятёрки. | H11: Встраиваемый виджет, версионирование, поддержка.
A12: Проверка позиций в поиске | B12: Диагностика | C12: 3 | D12: Ввод сайта и запросов — позиции в выдаче. | E12: Низкая | F12: Высокая | G12: Не рекомендую: нужен парсинг выдачи или платные API, результат нестабилен, а пользы для нашей продажи мало. | H12: Отказаться в пользу «Проверки сайта».
A13: Онлайн-конструктор сайта | B13: Инструмент | C13: 3 | D13: Собрать лендинг самому прямо на нашем сайте. | E13: Низкая | F13: Очень высокая | G13: Не рекомендую: конкуренция с Тильдой, месяцы разработки, и он уводит клиента от услуги, которой мы живём. | H13: Отказаться.
A15: Правило: сервис приносит заявки, только если требует данные пользователя и выдаёт персональный результат. Обезличенный «калькулятор стоимости сайта» с ползунком — декорация, её пролистывают.
